odoo/addons/partner_rank_single/README.rst
odoo/addons/partner_rank_single/__init__.py
odoo/addons/partner_rank_single/__manifest__.py
odoo/addons/partner_rank_single/i18n/it.po
odoo/addons/partner_rank_single/i18n/partner_rank_single.pot
odoo/addons/partner_rank_single/models/__init__.py
odoo/addons/partner_rank_single/models/res_partner.py
odoo/addons/partner_rank_single/readme/CONTRIBUTORS.md
odoo/addons/partner_rank_single/readme/CREDITS.md
odoo/addons/partner_rank_single/readme/DESCRIPTION.md
odoo/addons/partner_rank_single/static/description/icon.png
odoo/addons/partner_rank_single/static/description/index.html
odoo/addons/partner_rank_single/tests/__init__.py
odoo/addons/partner_rank_single/tests/test_partner_rank_single.py
odoo_addon_partner_rank_single-18.0.2.0.0.dist-info/METADATA
odoo_addon_partner_rank_single-18.0.2.0.0.dist-info/WHEEL
odoo_addon_partner_rank_single-18.0.2.0.0.dist-info/top_level.txt
odoo_addon_partner_rank_single-18.0.2.0.0.dist-info/RECORD
